rahil/__init__.py
rahil/data_manager.py
rahil/generator.py
rahil/lhs_sampler.py
rahil/data/finalized_params_for_run.xlsx
rahil_ctsm-0.1.0.dist-info/METADATA
rahil_ctsm-0.1.0.dist-info/WHEEL
rahil_ctsm-0.1.0.dist-info/top_level.txt
rahil_ctsm-0.1.0.dist-info/RECORD
