Metadata-Version: 2.4
Name: rahil-ctsm
Version: 0.1.0
Summary: Easy LHS parameter generator for CTSM/CLM crop calibration
Author-email: Mohammad Uzair Rahil <rahilmoh@msu.edu>
Requires-Python: >=3.9
Requires-Dist: numpy
Requires-Dist: pandas
Requires-Dist: xarray
Requires-Dist: netcdf4
Requires-Dist: openpyxl
Requires-Dist: requests
